onupoma_ai/__init__.py
onupoma_ai/ai.py
onupoma_ai-1.1.1.dist-info/METADATA
onupoma_ai-1.1.1.dist-info/WHEEL
onupoma_ai-1.1.1.dist-info/top_level.txt
onupoma_ai-1.1.1.dist-info/RECORD
